HandsON_BuildHat_API/SpikePI.py
HandsON_BuildHat_API/__init__.py
handson_buildhat_api-1.0.16.dist-info/licenses/LICENSE
handson_buildhat_api-1.0.16.dist-info/METADATA
handson_buildhat_api-1.0.16.dist-info/WHEEL
handson_buildhat_api-1.0.16.dist-info/top_level.txt
handson_buildhat_api-1.0.16.dist-info/RECORD
