Metadata-Version: 2.4
Name: HandsON-BuildHat-API
Version: 1.0.16
Summary: A third-party API for controlling LEGO SPIKE devices
Author-email: HaNeul Jung <hnjung@handsontech.co.kr>
License: Proprietary - Personal/Educational Use Only
Classifier: Programming Language :: Python :: 3
Classifier: License :: Other/Proprietary License
Classifier: Operating System :: OS Independent
Requires-Python: >=3.7
License-File: LICENSE
Requires-Dist: pyserial>=3.5
Dynamic: license-file
